spring_initializer/__init__.py
spring_initializer/__main__.py
spring_initializer/file_tools.py
spring_initializer/help.info
spring_initializer/main.py
spring_initializer-1.0.3.dist-info/licenses/LICENSE
spring_initializer-1.0.3.dist-info/METADATA
spring_initializer-1.0.3.dist-info/WHEEL
spring_initializer-1.0.3.dist-info/entry_points.txt
spring_initializer-1.0.3.dist-info/top_level.txt
spring_initializer-1.0.3.dist-info/RECORD
