Metadata-Version: 2.4
Name: spring-initializer
Version: 1.0.3
Summary: 下载并解压 Spring 框架代码
Home-page: https://github.com/icexmoon/spring-initializer
Author: icexmoon
Author-email: icexmoon@qq.com
Project-URL: Bug Tracker, https://github.com/icexmoon/spring-initializer/issues
Classifier: Programming Language :: Python :: 3
Classifier: License :: OSI Approved :: Apache Software License
Classifier: Operating System :: OS Independent
Requires-Python: >=3.6
License-File: LICENSE
Requires-Dist: requests
Dynamic: license-file
